{
  "modules": {
    "cce:/internal/x/cc": {
      "mTimestamp": 7864.892949000001,
      "chunkId": "909f786ffe128f06f5aa1b4e1e3fbbd65262915e",
      "imports": [
        {
          "value": "cce:/internal/x/cc-fu/2d",
          "resolved": "__unresolved_0",
          "loc": {
            "start": {
              "line": 1,
              "column": 14
            },
            "end": {
              "line": 1,
              "column": 40
            }
          }
        },
        {
          "value": "cce:/internal/x/cc-fu/animation",
          "resolved": "__unresolved_1",
          "loc": {
            "start": {
              "line": 2,
              "column": 14
            },
            "end": {
              "line": 2,
              "column": 47
            }
          }
        },
        {
          "value": "cce:/internal/x/cc-fu/audio",
          "resolved": "__unresolved_2",
          "loc": {
            "start": {
              "line": 3,
              "column": 14
            },
            "end": {
              "line": 3,
              "column": 43
            }
          }
        },
        {
          "value": "cce:/internal/x/cc-fu/base",
          "resolved": "__unresolved_3",
          "loc": {
            "start": {
              "line": 4,
              "column": 14
            },
            "end": {
              "line": 4,
              "column": 42
            }
          }
        },
        {
          "value": "cce:/internal/x/cc-fu/dragon-bones",
          "resolved": "__unresolved_4",
          "loc": {
            "start": {
              "line": 5,
              "column": 14
            },
            "end": {
              "line": 5,
              "column": 50
            }
          }
        },
        {
          "value": "cce:/internal/x/cc-fu/gfx-webgl",
          "resolved": "__unresolved_5",
          "loc": {
            "start": {
              "line": 6,
              "column": 14
            },
            "end": {
              "line": 6,
              "column": 47
            }
          }
        },
        {
          "value": "cce:/internal/x/cc-fu/gfx-webgl2",
          "resolved": "__unresolved_6",
          "loc": {
            "start": {
              "line": 7,
              "column": 14
            },
            "end": {
              "line": 7,
              "column": 48
            }
          }
        },
        {
          "value": "cce:/internal/x/cc-fu/intersection-2d",
          "resolved": "__unresolved_7",
          "loc": {
            "start": {
              "line": 8,
              "column": 14
            },
            "end": {
              "line": 8,
              "column": 53
            }
          }
        },
        {
          "value": "cce:/internal/x/cc-fu/particle-2d",
          "resolved": "__unresolved_8",
          "loc": {
            "start": {
              "line": 9,
              "column": 14
            },
            "end": {
              "line": 9,
              "column": 49
            }
          }
        },
        {
          "value": "cce:/internal/x/cc-fu/physics-2d-box2d",
          "resolved": "__unresolved_9",
          "loc": {
            "start": {
              "line": 10,
              "column": 14
            },
            "end": {
              "line": 10,
              "column": 54
            }
          }
        },
        {
          "value": "cce:/internal/x/cc-fu/physics-2d-framework",
          "resolved": "__unresolved_10",
          "loc": {
            "start": {
              "line": 11,
              "column": 14
            },
            "end": {
              "line": 11,
              "column": 58
            }
          }
        },
        {
          "value": "cce:/internal/x/cc-fu/profiler",
          "resolved": "__unresolved_11",
          "loc": {
            "start": {
              "line": 12,
              "column": 14
            },
            "end": {
              "line": 12,
              "column": 46
            }
          }
        },
        {
          "value": "cce:/internal/x/cc-fu/skeletal-animation",
          "resolved": "__unresolved_12",
          "loc": {
            "start": {
              "line": 13,
              "column": 14
            },
            "end": {
              "line": 13,
              "column": 56
            }
          }
        },
        {
          "value": "cce:/internal/x/cc-fu/spine",
          "resolved": "__unresolved_13",
          "loc": {
            "start": {
              "line": 14,
              "column": 14
            },
            "end": {
              "line": 14,
              "column": 43
            }
          }
        },
        {
          "value": "cce:/internal/x/cc-fu/tiled-map",
          "resolved": "__unresolved_14",
          "loc": {
            "start": {
              "line": 15,
              "column": 14
            },
            "end": {
              "line": 15,
              "column": 47
            }
          }
        },
        {
          "value": "cce:/internal/x/cc-fu/tween",
          "resolved": "__unresolved_15",
          "loc": {
            "start": {
              "line": 16,
              "column": 14
            },
            "end": {
              "line": 16,
              "column": 43
            }
          }
        },
        {
          "value": "cce:/internal/x/cc-fu/ui",
          "resolved": "__unresolved_16",
          "loc": {
            "start": {
              "line": 17,
              "column": 14
            },
            "end": {
              "line": 17,
              "column": 40
            }
          }
        },
        {
          "value": "cce:/internal/x/cc-fu/video",
          "resolved": "__unresolved_17",
          "loc": {
            "start": {
              "line": 18,
              "column": 14
            },
            "end": {
              "line": 18,
              "column": 43
            }
          }
        },
        {
          "value": "cce:/internal/x/cc-fu/webview",
          "resolved": "__unresolved_18",
          "loc": {
            "start": {
              "line": 19,
              "column": 14
            },
            "end": {
              "line": 19,
              "column": 45
            }
          }
        }
      ],
      "type": "esm",
      "resolutions": [
        {
          "resolved": {
            "type": "external",
            "specifierOrURL": "cce:/internal/x/cc-fu/2d"
          },
          "messages": []
        },
        {
          "resolved": {
            "type": "external",
            "specifierOrURL": "cce:/internal/x/cc-fu/animation"
          },
          "messages": []
        },
        {
          "resolved": {
            "type": "external",
            "specifierOrURL": "cce:/internal/x/cc-fu/audio"
          },
          "messages": []
        },
        {
          "resolved": {
            "type": "external",
            "specifierOrURL": "cce:/internal/x/cc-fu/base"
          },
          "messages": []
        },
        {
          "resolved": {
            "type": "external",
            "specifierOrURL": "cce:/internal/x/cc-fu/dragon-bones"
          },
          "messages": []
        },
        {
          "resolved": {
            "type": "external",
            "specifierOrURL": "cce:/internal/x/cc-fu/gfx-webgl"
          },
          "messages": []
        },
        {
          "resolved": {
            "type": "external",
            "specifierOrURL": "cce:/internal/x/cc-fu/gfx-webgl2"
          },
          "messages": []
        },
        {
          "resolved": {
            "type": "external",
            "specifierOrURL": "cce:/internal/x/cc-fu/intersection-2d"
          },
          "messages": []
        },
        {
          "resolved": {
            "type": "external",
            "specifierOrURL": "cce:/internal/x/cc-fu/particle-2d"
          },
          "messages": []
        },
        {
          "resolved": {
            "type": "external",
            "specifierOrURL": "cce:/internal/x/cc-fu/physics-2d-box2d"
          },
          "messages": []
        },
        {
          "resolved": {
            "type": "external",
            "specifierOrURL": "cce:/internal/x/cc-fu/physics-2d-framework"
          },
          "messages": []
        },
        {
          "resolved": {
            "type": "external",
            "specifierOrURL": "cce:/internal/x/cc-fu/profiler"
          },
          "messages": []
        },
        {
          "resolved": {
            "type": "external",
            "specifierOrURL": "cce:/internal/x/cc-fu/skeletal-animation"
          },
          "messages": []
        },
        {
          "resolved": {
            "type": "external",
            "specifierOrURL": "cce:/internal/x/cc-fu/spine"
          },
          "messages": []
        },
        {
          "resolved": {
            "type": "external",
            "specifierOrURL": "cce:/internal/x/cc-fu/tiled-map"
          },
          "messages": []
        },
        {
          "resolved": {
            "type": "external",
            "specifierOrURL": "cce:/internal/x/cc-fu/tween"
          },
          "messages": []
        },
        {
          "resolved": {
            "type": "external",
            "specifierOrURL": "cce:/internal/x/cc-fu/ui"
          },
          "messages": []
        },
        {
          "resolved": {
            "type": "external",
            "specifierOrURL": "cce:/internal/x/cc-fu/video"
          },
          "messages": []
        },
        {
          "resolved": {
            "type": "external",
            "specifierOrURL": "cce:/internal/x/cc-fu/webview"
          },
          "messages": []
        }
      ]
    },
    "cce:/internal/x/prerequisite-imports": {
      "mTimestamp": 8348.47378900001,
      "chunkId": "46cdbec9636fb7ec603b8064da54c9454d637e58",
      "imports": [
        {
          "value": "file:///Users/raopinwu/workspace/ccs/fitSreen/FitScreen/assets/Script/AutoScripts/Canvas.ts",
          "resolved": "__unresolved_0",
          "loc": {
            "start": {
              "line": 4,
              "column": 7
            },
            "end": {
              "line": 4,
              "column": 100
            }
          }
        },
        {
          "value": "file:///Users/raopinwu/workspace/ccs/fitSreen/FitScreen/assets/scripts/Main.ts",
          "resolved": "__unresolved_1",
          "loc": {
            "start": {
              "line": 5,
              "column": 7
            },
            "end": {
              "line": 5,
              "column": 87
            }
          }
        },
        {
          "value": "file:///Users/raopinwu/workspace/ccs/fitSreen/FitScreen/extensions/magic-book/assets/src/base/mb_base_cp.ts",
          "resolved": "__unresolved_2",
          "loc": {
            "start": {
              "line": 6,
              "column": 7
            },
            "end": {
              "line": 6,
              "column": 116
            }
          }
        },
        {
          "value": "file:///Users/raopinwu/workspace/ccs/fitSreen/FitScreen/extensions/magic-book/assets/src/common/base/mb_base.ts",
          "resolved": "__unresolved_3",
          "loc": {
            "start": {
              "line": 7,
              "column": 7
            },
            "end": {
              "line": 7,
              "column": 120
            }
          }
        },
        {
          "value": "file:///Users/raopinwu/workspace/ccs/fitSreen/FitScreen/extensions/magic-book/assets/src/common/decorator/mb_decorator.ts",
          "resolved": "__unresolved_4",
          "loc": {
            "start": {
              "line": 8,
              "column": 7
            },
            "end": {
              "line": 8,
              "column": 130
            }
          }
        },
        {
          "value": "file:///Users/raopinwu/workspace/ccs/fitSreen/FitScreen/extensions/magic-book/assets/src/common/log/mb_log.ts",
          "resolved": "__unresolved_5",
          "loc": {
            "start": {
              "line": 9,
              "column": 7
            },
            "end": {
              "line": 9,
              "column": 118
            }
          }
        },
        {
          "value": "file:///Users/raopinwu/workspace/ccs/fitSreen/FitScreen/extensions/magic-book/assets/src/config/mb_config.ts",
          "resolved": "__unresolved_6",
          "loc": {
            "start": {
              "line": 10,
              "column": 7
            },
            "end": {
              "line": 10,
              "column": 117
            }
          }
        },
        {
          "value": "file:///Users/raopinwu/workspace/ccs/fitSreen/FitScreen/extensions/magic-book/assets/src/mb.ts",
          "resolved": "__unresolved_7",
          "loc": {
            "start": {
              "line": 11,
              "column": 7
            },
            "end": {
              "line": 11,
              "column": 103
            }
          }
        },
        {
          "value": "file:///Users/raopinwu/workspace/ccs/fitSreen/FitScreen/extensions/magic-book/assets/src/system/audio/mb_audio.ts",
          "resolved": "__unresolved_8",
          "loc": {
            "start": {
              "line": 12,
              "column": 7
            },
            "end": {
              "line": 12,
              "column": 122
            }
          }
        },
        {
          "value": "file:///Users/raopinwu/workspace/ccs/fitSreen/FitScreen/extensions/magic-book/assets/src/system/audio/mb_audio_volume_cp.ts",
          "resolved": "__unresolved_9",
          "loc": {
            "start": {
              "line": 13,
              "column": 7
            },
            "end": {
              "line": 13,
              "column": 132
            }
          }
        }
      ],
      "type": "esm",
      "resolutions": [
        {
          "resolved": {
            "type": "module",
            "url": "file:///Users/raopinwu/workspace/ccs/fitSreen/FitScreen/assets/Script/AutoScripts/Canvas.ts"
          },
          "messages": []
        },
        {
          "resolved": {
            "type": "module",
            "url": "file:///Users/raopinwu/workspace/ccs/fitSreen/FitScreen/assets/scripts/Main.ts"
          },
          "messages": []
        },
        {
          "resolved": {
            "type": "module",
            "url": "file:///Users/raopinwu/workspace/ccs/fitSreen/FitScreen/extensions/magic-book/assets/src/base/mb_base_cp.ts"
          },
          "messages": []
        },
        {
          "resolved": {
            "type": "module",
            "url": "file:///Users/raopinwu/workspace/ccs/fitSreen/FitScreen/extensions/magic-book/assets/src/common/base/mb_base.ts"
          },
          "messages": []
        },
        {
          "resolved": {
            "type": "module",
            "url": "file:///Users/raopinwu/workspace/ccs/fitSreen/FitScreen/extensions/magic-book/assets/src/common/decorator/mb_decorator.ts"
          },
          "messages": []
        },
        {
          "resolved": {
            "type": "module",
            "url": "file:///Users/raopinwu/workspace/ccs/fitSreen/FitScreen/extensions/magic-book/assets/src/common/log/mb_log.ts"
          },
          "messages": []
        },
        {
          "resolved": {
            "type": "module",
            "url": "file:///Users/raopinwu/workspace/ccs/fitSreen/FitScreen/extensions/magic-book/assets/src/config/mb_config.ts"
          },
          "messages": []
        },
        {
          "resolved": {
            "type": "module",
            "url": "file:///Users/raopinwu/workspace/ccs/fitSreen/FitScreen/extensions/magic-book/assets/src/mb.ts"
          },
          "messages": []
        },
        {
          "resolved": {
            "type": "module",
            "url": "file:///Users/raopinwu/workspace/ccs/fitSreen/FitScreen/extensions/magic-book/assets/src/system/audio/mb_audio.ts"
          },
          "messages": []
        },
        {
          "resolved": {
            "type": "module",
            "url": "file:///Users/raopinwu/workspace/ccs/fitSreen/FitScreen/extensions/magic-book/assets/src/system/audio/mb_audio_volume_cp.ts"
          },
          "messages": []
        }
      ]
    },
    "file:///Users/raopinwu/workspace/ccs/fitSreen/FitScreen/assets/scripts/Main.ts": {
      "mTimestamp": {
        "mtime": 1661658221270.8765,
        "uuid": "b87fb8cb-fb8b-47f2-8f38-008fe2d40546"
      },
      "chunkId": "bfa51286ad5848ef6e13a9d3f8112fb6fd93f4ad",
      "imports": [
        {
          "value": "cc"
        },
        {
          "value": "cc"
        },
        {
          "value": "cc",
          "loc": {
            "start": {
              "line": 1,
              "column": 93
            },
            "end": {
              "line": 1,
              "column": 97
            }
          }
        }
      ],
      "type": "esm",
      "resolutions": [
        {
          "resolved": {
            "type": "module",
            "url": "cce:/internal/x/cc"
          },
          "messages": []
        },
        {
          "resolved": {
            "type": "module",
            "url": "cce:/internal/x/cc"
          },
          "messages": []
        },
        {
          "resolved": {
            "type": "module",
            "url": "cce:/internal/x/cc"
          },
          "messages": []
        }
      ]
    },
    "file:///Users/raopinwu/workspace/ccs/fitSreen/FitScreen/assets/Script/AutoScripts/Canvas.ts": {
      "mTimestamp": {
        "mtime": 1661788134810.557,
        "uuid": "39b92839-b6e3-4b9e-83f6-7bf5b064e954"
      },
      "chunkId": "d9cb942cb4e31d060b6152fdf08c59cdb49deabe",
      "imports": [
        {
          "value": "cc"
        },
        {
          "value": "cc"
        },
        {
          "value": "cc",
          "loc": {
            "start": {
              "line": 3,
              "column": 45
            },
            "end": {
              "line": 3,
              "column": 49
            }
          }
        }
      ],
      "type": "esm",
      "resolutions": [
        {
          "resolved": {
            "type": "module",
            "url": "cce:/internal/x/cc"
          },
          "messages": []
        },
        {
          "resolved": {
            "type": "module",
            "url": "cce:/internal/x/cc"
          },
          "messages": []
        },
        {
          "resolved": {
            "type": "module",
            "url": "cce:/internal/x/cc"
          },
          "messages": []
        }
      ]
    },
    "file:///Users/raopinwu/workspace/ccs/fitSreen/FitScreen/assets/Script/AutoScripts/Button@leftUp.ts": {
      "erroneous": true,
      "mTimestamp": {
        "mtime": 1661758823840.467,
        "uuid": "8f7643c5-aaa5-4954-9c36-0d047063953b"
      },
      "chunkId": "d781a127d468a6837ee3fd340a36564bc3110272"
    },
    "file:///Users/raopinwu/workspace/ccs/fitSreen/FitScreen/extensions/magic-book/assets/src/base/mb_base_cp.ts": {
      "mTimestamp": {
        "mtime": 1660483638000,
        "uuid": "b3a6b1ee-4e2b-4517-a3f0-ff39d34681ee"
      },
      "chunkId": "37c378cd3d31091f02218c4bed9038831a60bf9d",
      "imports": [
        {
          "value": "cc"
        },
        {
          "value": "cc"
        },
        {
          "value": "cc",
          "loc": {
            "start": {
              "line": 1,
              "column": 52
            },
            "end": {
              "line": 1,
              "column": 56
            }
          }
        }
      ],
      "type": "esm",
      "resolutions": [
        {
          "resolved": {
            "type": "module",
            "url": "cce:/internal/x/cc"
          },
          "messages": []
        },
        {
          "resolved": {
            "type": "module",
            "url": "cce:/internal/x/cc"
          },
          "messages": []
        },
        {
          "resolved": {
            "type": "module",
            "url": "cce:/internal/x/cc"
          },
          "messages": []
        }
      ]
    },
    "file:///Users/raopinwu/workspace/ccs/fitSreen/FitScreen/extensions/magic-book/assets/src/common/base/mb_base.ts": {
      "mTimestamp": {
        "mtime": 1660483638000,
        "uuid": "36c69550-d36f-4261-ac4c-90c76ec6d3ac"
      },
      "chunkId": "c8bb897b1bf9b5b410340c49a74ffcf88afbebc0",
      "imports": [
        {
          "value": "cce:/internal/code-quality/cr.mjs",
          "resolved": "__unresolved_0"
        },
        {
          "value": "cc"
        },
        {
          "value": "../../mb",
          "resolved": "__unresolved_1",
          "loc": {
            "start": {
              "line": 1,
              "column": 15
            },
            "end": {
              "line": 1,
              "column": 25
            }
          }
        },
        {
          "value": "../log/mb_log",
          "resolved": "__unresolved_2",
          "loc": {
            "start": {
              "line": 2,
              "column": 19
            },
            "end": {
              "line": 2,
              "column": 34
            }
          }
        }
      ],
      "type": "esm",
      "resolutions": [
        {
          "resolved": {
            "type": "module",
            "url": "cce:/internal/code-quality/cr.mjs"
          },
          "messages": []
        },
        {
          "resolved": {
            "type": "module",
            "url": "cce:/internal/x/cc"
          },
          "messages": []
        },
        {
          "resolved": {
            "type": "module",
            "url": "file:///Users/raopinwu/workspace/ccs/fitSreen/FitScreen/extensions/magic-book/assets/src/mb.ts"
          },
          "messages": []
        },
        {
          "resolved": {
            "type": "module",
            "url": "file:///Users/raopinwu/workspace/ccs/fitSreen/FitScreen/extensions/magic-book/assets/src/common/log/mb_log.ts"
          },
          "messages": []
        }
      ]
    },
    "cce:/internal/code-quality/cr.mjs": {
      "mTimestamp": 1661817176771,
      "chunkId": "3a1fd7b13056478820ebedd306d3446d1aa408cc",
      "imports": [],
      "type": "esm",
      "resolutions": []
    },
    "file:///Users/raopinwu/workspace/ccs/fitSreen/FitScreen/extensions/magic-book/assets/src/mb.ts": {
      "mTimestamp": {
        "mtime": 1660483638000,
        "uuid": "d14f9699-3135-48b0-84fb-d78a42c2ab33"
      },
      "chunkId": "6a545531ef3bb8ed02161a2586b1d57eb088b99d",
      "imports": [
        {
          "value": "cce:/internal/code-quality/cr.mjs",
          "resolved": "__unresolved_0"
        },
        {
          "value": "cc"
        },
        {
          "value": "./config/mb_config",
          "resolved": "__unresolved_1",
          "loc": {
            "start": {
              "line": 1,
              "column": 22
            },
            "end": {
              "line": 1,
              "column": 42
            }
          }
        },
        {
          "value": "./system/audio/mb_audio",
          "resolved": "__unresolved_2",
          "loc": {
            "start": {
              "line": 2,
              "column": 21
            },
            "end": {
              "line": 2,
              "column": 46
            }
          }
        }
      ],
      "type": "esm",
      "resolutions": [
        {
          "resolved": {
            "type": "module",
            "url": "cce:/internal/code-quality/cr.mjs"
          },
          "messages": []
        },
        {
          "resolved": {
            "type": "module",
            "url": "cce:/internal/x/cc"
          },
          "messages": []
        },
        {
          "resolved": {
            "type": "module",
            "url": "file:///Users/raopinwu/workspace/ccs/fitSreen/FitScreen/extensions/magic-book/assets/src/config/mb_config.ts"
          },
          "messages": []
        },
        {
          "resolved": {
            "type": "module",
            "url": "file:///Users/raopinwu/workspace/ccs/fitSreen/FitScreen/extensions/magic-book/assets/src/system/audio/mb_audio.ts"
          },
          "messages": []
        }
      ]
    },
    "file:///Users/raopinwu/workspace/ccs/fitSreen/FitScreen/extensions/magic-book/assets/src/config/mb_config.ts": {
      "mTimestamp": {
        "mtime": 1660483638000,
        "uuid": "07acc4ab-957c-418b-8fff-5c7f0adccc3b"
      },
      "chunkId": "e4189078892f1e98585c2bb07b7bbef852f46238",
      "imports": [
        {
          "value": "cc"
        }
      ],
      "type": "esm",
      "resolutions": [
        {
          "resolved": {
            "type": "module",
            "url": "cce:/internal/x/cc"
          },
          "messages": []
        }
      ]
    },
    "file:///Users/raopinwu/workspace/ccs/fitSreen/FitScreen/extensions/magic-book/assets/src/system/audio/mb_audio.ts": {
      "mTimestamp": {
        "mtime": 1660485772000,
        "uuid": "5d9ddd02-7ef7-4f4b-a5bc-da71c9cb9e34"
      },
      "chunkId": "48eb07f6e5e5f81f19bd296b82042bba678edebc",
      "imports": [
        {
          "value": "cce:/internal/code-quality/cr.mjs",
          "resolved": "__unresolved_0"
        },
        {
          "value": "cc"
        },
        {
          "value": "cc"
        },
        {
          "value": "cc",
          "loc": {
            "start": {
              "line": 1,
              "column": 69
            },
            "end": {
              "line": 1,
              "column": 73
            }
          }
        },
        {
          "value": "../../common/base/mb_base",
          "resolved": "__unresolved_1",
          "loc": {
            "start": {
              "line": 2,
              "column": 20
            },
            "end": {
              "line": 2,
              "column": 47
            }
          }
        },
        {
          "value": "../../common/decorator/mb_decorator",
          "resolved": "__unresolved_2",
          "loc": {
            "start": {
              "line": 3,
              "column": 25
            },
            "end": {
              "line": 3,
              "column": 62
            }
          }
        }
      ],
      "type": "esm",
      "resolutions": [
        {
          "resolved": {
            "type": "module",
            "url": "cce:/internal/code-quality/cr.mjs"
          },
          "messages": []
        },
        {
          "resolved": {
            "type": "module",
            "url": "cce:/internal/x/cc"
          },
          "messages": []
        },
        {
          "resolved": {
            "type": "module",
            "url": "cce:/internal/x/cc"
          },
          "messages": []
        },
        {
          "resolved": {
            "type": "module",
            "url": "cce:/internal/x/cc"
          },
          "messages": []
        },
        {
          "resolved": {
            "type": "module",
            "url": "file:///Users/raopinwu/workspace/ccs/fitSreen/FitScreen/extensions/magic-book/assets/src/common/base/mb_base.ts"
          },
          "messages": []
        },
        {
          "resolved": {
            "type": "module",
            "url": "file:///Users/raopinwu/workspace/ccs/fitSreen/FitScreen/extensions/magic-book/assets/src/common/decorator/mb_decorator.ts"
          },
          "messages": []
        }
      ]
    },
    "file:///Users/raopinwu/workspace/ccs/fitSreen/FitScreen/extensions/magic-book/assets/src/common/decorator/mb_decorator.ts": {
      "mTimestamp": {
        "mtime": 1660483638000,
        "uuid": "2791e0ae-7e74-4cb9-9967-fde96fe78787"
      },
      "chunkId": "16c7c499ea2b763103937ecf711b669498cd7fce",
      "imports": [
        {
          "value": "cce:/internal/code-quality/cr.mjs",
          "resolved": "__unresolved_0"
        },
        {
          "value": "cc"
        },
        {
          "value": "../base/mb_base",
          "resolved": "__unresolved_1",
          "loc": {
            "start": {
              "line": 1,
              "column": 20
            },
            "end": {
              "line": 1,
              "column": 37
            }
          }
        }
      ],
      "type": "esm",
      "resolutions": [
        {
          "resolved": {
            "type": "module",
            "url": "cce:/internal/code-quality/cr.mjs"
          },
          "messages": []
        },
        {
          "resolved": {
            "type": "module",
            "url": "cce:/internal/x/cc"
          },
          "messages": []
        },
        {
          "resolved": {
            "type": "module",
            "url": "file:///Users/raopinwu/workspace/ccs/fitSreen/FitScreen/extensions/magic-book/assets/src/common/base/mb_base.ts"
          },
          "messages": []
        }
      ]
    },
    "file:///Users/raopinwu/workspace/ccs/fitSreen/FitScreen/extensions/magic-book/assets/src/common/log/mb_log.ts": {
      "mTimestamp": {
        "mtime": 1660483638000,
        "uuid": "9a38f7d0-2bb0-4ad0-a0a2-f37a8b6551b0"
      },
      "chunkId": "bb5834cd5f14559deb337129c8f2d640109fa2fd",
      "imports": [
        {
          "value": "cce:/internal/code-quality/cr.mjs",
          "resolved": "__unresolved_0"
        },
        {
          "value": "cc"
        },
        {
          "value": "../../mb",
          "resolved": "__unresolved_1",
          "loc": {
            "start": {
              "line": 1,
              "column": 15
            },
            "end": {
              "line": 1,
              "column": 25
            }
          }
        }
      ],
      "type": "esm",
      "resolutions": [
        {
          "resolved": {
            "type": "module",
            "url": "cce:/internal/code-quality/cr.mjs"
          },
          "messages": []
        },
        {
          "resolved": {
            "type": "module",
            "url": "cce:/internal/x/cc"
          },
          "messages": []
        },
        {
          "resolved": {
            "type": "module",
            "url": "file:///Users/raopinwu/workspace/ccs/fitSreen/FitScreen/extensions/magic-book/assets/src/mb.ts"
          },
          "messages": []
        }
      ]
    },
    "file:///Users/raopinwu/workspace/ccs/fitSreen/FitScreen/extensions/magic-book/assets/src/system/audio/mb_audio_volume_cp.ts": {
      "mTimestamp": {
        "mtime": 1660483638000,
        "uuid": "8c3de529-79d5-49a7-bba4-e3e4d02d301b"
      },
      "chunkId": "c11517d640943a44ea3342c401fb0be0f74ccb2f",
      "imports": [
        {
          "value": "cce:/internal/code-quality/cr.mjs",
          "resolved": "__unresolved_0"
        },
        {
          "value": "cc"
        },
        {
          "value": "cc"
        },
        {
          "value": "cc",
          "loc": {
            "start": {
              "line": 2,
              "column": 64
            },
            "end": {
              "line": 2,
              "column": 68
            }
          }
        },
        {
          "value": "../../base/mb_base_cp",
          "resolved": "__unresolved_1",
          "loc": {
            "start": {
              "line": 3,
              "column": 27
            },
            "end": {
              "line": 3,
              "column": 50
            }
          }
        },
        {
          "value": "../../mb",
          "resolved": "__unresolved_2",
          "loc": {
            "start": {
              "line": 4,
              "column": 15
            },
            "end": {
              "line": 4,
              "column": 25
            }
          }
        }
      ],
      "type": "esm",
      "resolutions": [
        {
          "resolved": {
            "type": "module",
            "url": "cce:/internal/code-quality/cr.mjs"
          },
          "messages": []
        },
        {
          "resolved": {
            "type": "module",
            "url": "cce:/internal/x/cc"
          },
          "messages": []
        },
        {
          "resolved": {
            "type": "module",
            "url": "cce:/internal/x/cc"
          },
          "messages": []
        },
        {
          "resolved": {
            "type": "module",
            "url": "cce:/internal/x/cc"
          },
          "messages": []
        },
        {
          "resolved": {
            "type": "module",
            "url": "file:///Users/raopinwu/workspace/ccs/fitSreen/FitScreen/extensions/magic-book/assets/src/base/mb_base_cp.ts"
          },
          "messages": []
        },
        {
          "resolved": {
            "type": "module",
            "url": "file:///Users/raopinwu/workspace/ccs/fitSreen/FitScreen/extensions/magic-book/assets/src/mb.ts"
          },
          "messages": []
        }
      ]
    },
    "file:///Users/raopinwu/workspace/ccs/fitSreen/FitScreen/assets/Script/AutoScripts/Button@Button1.ts": {
      "erroneous": true,
      "mTimestamp": {
        "mtime": 1661788096059.453,
        "uuid": "d4634a24-cf3f-49aa-886d-64d21059efce"
      },
      "chunkId": "c6ab0b34d50f6b28801340e7d602f9d22afb2c78"
    }
  }
}
